LICENSE.txt
MANIFEST.in
README.rst
setup.py
django_genes.egg-info/PKG-INFO
django_genes.egg-info/SOURCES.txt
django_genes.egg-info/dependency_links.txt
django_genes.egg-info/requires.txt
django_genes.egg-info/top_level.txt
genes/__init__.py
genes/api.py
genes/app_settings.py
genes/models.py
genes/search_indexes.py
genes/tests.py
genes/utils.py
genes/management/__init__.py
genes/management/commands/__init__.py
genes/management/commands/genes_add_xrdb.py
genes/management/commands/genes_load_gene_history.py
genes/management/commands/genes_load_geneinfo.py
genes/management/commands/genes_load_uniprot.py
genes/management/commands/genes_load_wb.py
genes/migrations/0001_initial.py
genes/migrations/__init__.py
genes/templates/search/indexes/genes/gene_text.txt