Metadata-Version: 1.1
Name: django-genes
Version: 0.17
Summary: A simple Django app to represent genes.
Home-page: https://github.com/greenelab/django-genes
Author: Greene Lab
Author-email: team@greenelab.com
License: LICENSE.txt
Platform: UNKNOWN
Classifier: Environment :: Web Environment
Classifier: Framework :: Django
Classifier: Intended Audience :: Developers
Classifier: License :: OSI Approved :: BSD License
Classifier: Operating System :: OS Independent
Classifier: Programming Language :: Python
Classifier: Programming Language :: Python :: 2.7
Classifier: Topic :: Scientific/Engineering :: Bio-Informatics
